[
    {
        "flow": "Industry", 
        "product": "Coal and coal products", 
        "value": 5.404760438356164
    }, 
    {
        "flow": "Industry", 
        "product": "Gas", 
        "value": 114.56057000000001
    }, 
    {
        "flow": "Industry", 
        "product": "Combustible renewables and waste", 
        "value": 44.6113238630137
    }, 
    {
        "flow": "Transport", 
        "product": "Gas", 
        "value": 61.9845685479452
    }, 
    {
        "flow": "Residential", 
        "product": "Gas", 
        "value": 115.31537926027399
    }, 
    {
        "flow": "Residential", 
        "product": "Combustible renewables and waste", 
        "value": 6.523720082191781
    }, 
    {
        "flow": "Commercial", 
        "product": "Gas", 
        "value": 17.16123698630137
    }, 
    {
        "flow": "Commercial", 
        "product": "Combustible renewables and waste", 
        "value": 1.590710410958904
    }, 
    {
        "flow": "Other", 
        "product": "Gas", 
        "value": 32.372212000000005
    }, 
    {
        "flow": "Other", 
        "product": "Combustible renewables and waste", 
        "value": 1.2022605753424658
    }, 
    {
        "flow": "Industry", 
        "product": "Oil Products", 
        "value": 84.59723698630137
    }, 
    {
        "flow": "Transport", 
        "product": "Oil Products", 
        "value": 184.56506224657534
    }, 
    {
        "flow": "Residential", 
        "product": "Oil Products", 
        "value": 18.141127452054796
    }, 
    {
        "flow": "Commercial", 
        "product": "Oil Products", 
        "value": 4.7875945205479455
    }, 
    {
        "flow": "Other", 
        "product": "Oil Products", 
        "value": 109.57635073972602
    }, 
    {
        "flow": "Industry", 
        "product": "Electricity", 
        "value": 66.0672781369863
    }, 
    {
        "flow": "Transport", 
        "product": "Electricity", 
        "value": 0.9343440547945207
    }, 
    {
        "flow": "Residential", 
        "product": "Electricity", 
        "value": 37.26495687671233
    }, 
    {
        "flow": "Commercial", 
        "product": "Electricity", 
        "value": 33.77282438356165
    }, 
    {
        "flow": "Other", 
        "product": "Electricity", 
        "value": 1.0172433424657534
    }, 
    {
        "flow": "Electricity output in GWh", 
        "product": "Coal and coal products", 
        "value": 930.0
    }, 
    {
        "flow": "Electricity output in GWh", 
        "product": "Gas", 
        "value": 47594.0
    }, 
    {
        "flow": "Electricity output in GWh", 
        "product": "Nuclear", 
        "value": 7566.0
    }, 
    {
        "flow": "Electricity output in GWh", 
        "product": "Hydro", 
        "value": 33813.0
    }, 
    {
        "flow": "Electricity output in GWh", 
        "product": "Solar/Wind/Other", 
        "value": 78.0
    }, 
    {
        "flow": "Electricity output in GWh", 
        "product": "Combustible renewables and waste", 
        "value": 1036.0
    }, 
    {
        "flow": "Electricity output in GWh", 
        "product": "Oil Products", 
        "value": 1011.0
    }, 
    {
        "flow": "Production", 
        "product": "Coal and coal products", 
        "value": 1.0545158904109588
    }, 
    {
        "flow": "Production", 
        "product": "Crude, NGL and feedstocks", 
        "value": 810.7309950410958
    }, 
    {
        "flow": "Production", 
        "product": "Gas", 
        "value": 718.1729362465753
    }, 
    {
        "flow": "Production", 
        "product": "Nuclear", 
        "value": 39.59696123287671
    }, 
    {
        "flow": "Production", 
        "product": "Hydro", 
        "value": 58.397366958904115
    }, 
    {
        "flow": "Production", 
        "product": "Solar/Wind/Other", 
        "value": 0.13471134246575342
    }, 
    {
        "flow": "Production", 
        "product": "Combustible renewables and waste", 
        "value": 64.20049783561645
    }, 
    {
        "flow": "Imports", 
        "product": "Coal and coal products", 
        "value": 11.928842
    }, 
    {
        "flow": "Imports", 
        "product": "Crude, NGL and feedstocks", 
        "value": 4.940219178082192
    }, 
    {
        "flow": "Imports", 
        "product": "Gas", 
        "value": 1.5273109315068492
    }, 
    {
        "flow": "Exports", 
        "product": "Coal and coal products", 
        "value": -2.948407150684932
    }, 
    {
        "flow": "Exports", 
        "product": "Crude, NGL and feedstocks", 
        "value": -231.02553424657538
    }, 
    {
        "flow": "Exports", 
        "product": "Gas", 
        "value": -113.75095643835618
    }, 
    {
        "flow": "Total Consumption", 
        "product": "Coal and coal products", 
        "value": 5.404760438356164
    }, 
    {
        "flow": "Total Consumption", 
        "product": "Gas", 
        "value": 341.39396679452057
    }, 
    {
        "flow": "Total Consumption", 
        "product": "Combustible renewables and waste", 
        "value": 53.928035013698626
    }, 
    {
        "flow": "Imports", 
        "product": "Oil Products", 
        "value": 7.017460849315069
    }, 
    {
        "flow": "Imports", 
        "product": "Electricity", 
        "value": 13.087725041095888
    }, 
    {
        "flow": "Exports", 
        "product": "Oil Products", 
        "value": -169.55774073972606
    }, 
    {
        "flow": "Exports", 
        "product": "Electricity", 
        "value": -4.391935178082192
    }, 
    {
        "flow": "Total Consumption", 
        "product": "Oil Products", 
        "value": 401.66737194520545
    }, 
    {
        "flow": "Total Consumption", 
        "product": "Electricity", 
        "value": 139.05664679452056
    }, 
    {
        "flow": "Production", 
        "product": "Electricity", 
        "value": 311.47565805479456
    }, 
    {
        "flow": "Electricity", 
        "product": "Coal and coal products", 
        "value": -5.078565397260274
    }, 
    {
        "flow": "Electricity", 
        "product": "Gas", 
        "value": -193.73744268493152
    }, 
    {
        "flow": "Electricity", 
        "product": "Nuclear", 
        "value": -39.59696123287671
    }, 
    {
        "flow": "Electricity", 
        "product": "Hydro", 
        "value": -58.39736695890411
    }, 
    {
        "flow": "Electricity", 
        "product": "Solar/Wind/Other", 
        "value": -0.13471134246575342
    }, 
    {
        "flow": "Electricity", 
        "product": "Combustible renewables and waste", 
        "value": -7.091303068493151
    }, 
    {
        "flow": "Electricity", 
        "product": "Oil Products", 
        "value": -7.439307369863014
    }, 
    {
        "flow": "Oil Products", 
        "product": "Crude, NGL and feedstocks", 
        "value": -565.4141095890411
    }, 
    {
        "flow": "Heat and Waste", 
        "product": "All products", 
        "value": 178.29110438356167
    }, 
    {
        "flow": "Industry", 
        "product": "All products", 
        "value": 315.2411694246575
    }, 
    {
        "flow": "Transport", 
        "product": "All products", 
        "value": 247.48397484931505
    }, 
    {
        "flow": "Residential", 
        "product": "All products", 
        "value": 177.24518367123287
    }, 
    {
        "flow": "Commercial", 
        "product": "All products", 
        "value": 57.31236630136986
    }, 
    {
        "flow": "Other", 
        "product": "All products", 
        "value": 144.16808673972602
    }, 
    {
        "flow": "Total Consumption", 
        "product": "All products", 
        "value": 941.4507809863014
    }, 
    {
        "flow": "Production", 
        "product": "All primary", 
        "value": 1692.2879845479451
    }, 
    {
        "flow": "Imports", 
        "product": "All primary", 
        "value": 18.39637210958904
    }, 
    {
        "flow": "Exports", 
        "product": "All primary", 
        "value": -347.7248978356165
    }, 
    {
        "flow": "Total Consumption", 
        "product": "All primary", 
        "value": 400.72676224657533
    }, 
    {
        "flow": "Oil Products", 
        "product": "All primary", 
        "value": -565.4141095890411
    }, 
    {
        "flow": "Electricity", 
        "product": "All primary", 
        "value": -311.47565805479456
    }, 
    {
        "flow": "Production", 
        "product": "Oil Products", 
        "value": 563.9235892328767
    }, 
    {
        "flow": "Hydrocarbon Heat and Waste", 
        "product": "All products", 
        "value": 1.4905203561644385
    }, 
    {
        "flow": "Electricity Heat and Waste", 
        "product": "All products", 
        "value": 176.80058402739724
    }
]
