[
    {
        "flow": "Electricity output in GWh", 
        "period": "1998", 
        "value": 1.0
    }, 
    {
        "flow": "Production", 
        "period": "1998", 
        "value": 0.008635342465753424
    }, 
    {
        "flow": "Electricity", 
        "period": "1998", 
        "value": -0.008635342465753424
    }, 
    {
        "flow": "Electricity output in GWh", 
        "period": "2003", 
        "value": 195.0
    }, 
    {
        "flow": "Production", 
        "period": "2003", 
        "value": 3.3670003561643838
    }, 
    {
        "flow": "Electricity", 
        "period": "2003", 
        "value": -3.3670003561643838
    }, 
    {
        "flow": "Electricity output in GWh", 
        "period": "2004", 
        "value": 194.0
    }, 
    {
        "flow": "Production", 
        "period": "2004", 
        "value": 3.3531034794520544
    }, 
    {
        "flow": "Electricity", 
        "period": "2004", 
        "value": -3.3531034794520544
    }, 
    {
        "flow": "Electricity output in GWh", 
        "period": "2009", 
        "value": 387.0
    }, 
    {
        "flow": "Production", 
        "period": "2009", 
        "value": 6.674557424657535
    }, 
    {
        "flow": "Electricity", 
        "period": "2009", 
        "value": -6.674557424657535
    }, 
    {
        "flow": "Electricity output in GWh", 
        "period": "2010", 
        "value": 271.0
    }, 
    {
        "flow": "Production", 
        "period": "2010", 
        "value": 4.678608465753425
    }, 
    {
        "flow": "Electricity", 
        "period": "2010", 
        "value": -4.678608465753425
    }, 
    {
        "flow": "Electricity output in GWh", 
        "period": "2011", 
        "value": 147.0
    }, 
    {
        "flow": "Production", 
        "period": "2011", 
        "value": 2.535918931506849
    }, 
    {
        "flow": "Electricity", 
        "period": "2011", 
        "value": -2.535918931506849
    }, 
    {
        "flow": "Electricity output in GWh", 
        "period": "2012", 
        "value": 246.0
    }, 
    {
        "flow": "Production", 
        "period": "2012", 
        "value": 4.247002
    }, 
    {
        "flow": "Electricity", 
        "period": "2012", 
        "value": -4.247002
    }, 
    {
        "flow": "Electricity output in GWh", 
        "period": "2013", 
        "value": 212.0
    }, 
    {
        "flow": "Production", 
        "period": "2013", 
        "value": 3.660019616438356
    }, 
    {
        "flow": "Electricity", 
        "period": "2013", 
        "value": -3.660019616438356
    }, 
    {
        "flow": "Electricity output in GWh", 
        "period": "2014", 
        "value": 247.0
    }, 
    {
        "flow": "Production", 
        "period": "2014", 
        "value": 4.264272684931507
    }, 
    {
        "flow": "Electricity", 
        "period": "2014", 
        "value": -4.264272684931507
    }, 
    {
        "flow": "Electricity output in GWh", 
        "period": "2015", 
        "value": 252.0
    }, 
    {
        "flow": "Production", 
        "period": "2015", 
        "value": 4.35058594520548
    }, 
    {
        "flow": "Electricity", 
        "period": "2015", 
        "value": -4.35058594520548
    }, 
    {
        "flow": "Electricity output in GWh", 
        "period": "2016", 
        "value": 339.0
    }, 
    {
        "flow": "Production", 
        "period": "2016", 
        "value": 5.853717917808219
    }, 
    {
        "flow": "Electricity", 
        "period": "2016", 
        "value": -5.853717917808219
    }
]
