[
    {
        "flow": "Industry", 
        "product": "Coal and coal products", 
        "value": 18.981145452054793
    }, 
    {
        "flow": "Transport", 
        "product": "Coal and coal products", 
        "value": 0.02691013698630137
    }, 
    {
        "flow": "Residential", 
        "product": "Coal and coal products", 
        "value": 2.1979155616438355
    }, 
    {
        "flow": "Other", 
        "product": "Coal and coal products", 
        "value": 0.9687649315068493
    }, 
    {
        "flow": "Industry", 
        "product": "Combustible renewables and waste", 
        "value": 62.845251123287674
    }, 
    {
        "flow": "Residential", 
        "product": "Combustible renewables and waste", 
        "value": 8.010625643835617
    }, 
    {
        "flow": "Industry", 
        "product": "Oil Products", 
        "value": 112.54929832876712
    }, 
    {
        "flow": "Transport", 
        "product": "Oil Products", 
        "value": 104.69274326027397
    }, 
    {
        "flow": "Residential", 
        "product": "Oil Products", 
        "value": 165.2051465753425
    }, 
    {
        "flow": "Commercial", 
        "product": "Oil Products", 
        "value": 0.3530248493150685
    }, 
    {
        "flow": "Other", 
        "product": "Oil Products", 
        "value": 82.99815230136986
    }, 
    {
        "flow": "Industry", 
        "product": "Electricity", 
        "value": 66.8410048219178
    }, 
    {
        "flow": "Transport", 
        "product": "Electricity", 
        "value": 3.5301279999999995
    }, 
    {
        "flow": "Residential", 
        "product": "Electricity", 
        "value": 29.938732328767124
    }, 
    {
        "flow": "Commercial", 
        "product": "Electricity", 
        "value": 22.037393972602736
    }, 
    {
        "flow": "Other", 
        "product": "Electricity", 
        "value": 1.4179232328767124
    }, 
    {
        "flow": "Other", 
        "product": "Heat", 
        "value": 19.241009013698633
    }, 
    {
        "flow": "Electricity output in GWh", 
        "product": "Coal and coal products", 
        "value": 310.0
    }, 
    {
        "flow": "Electricity output in GWh", 
        "product": "Nuclear", 
        "value": 11969.0
    }, 
    {
        "flow": "Electricity output in GWh", 
        "product": "Hydro", 
        "value": 57648.0
    }, 
    {
        "flow": "Electricity output in GWh", 
        "product": "Combustible renewables and waste", 
        "value": 310.0
    }, 
    {
        "flow": "Electricity output in GWh", 
        "product": "Oil Products", 
        "value": 10315.0
    }, 
    {
        "flow": "Production", 
        "product": "Coal and coal products", 
        "value": 1.1167907671232877
    }, 
    {
        "flow": "Production", 
        "product": "Nuclear", 
        "value": 62.640252109589035
    }, 
    {
        "flow": "Production", 
        "product": "Hydro", 
        "value": 99.5620444931507
    }, 
    {
        "flow": "Production", 
        "product": "Combustible renewables and waste", 
        "value": 71.61982342465754
    }, 
    {
        "flow": "Imports", 
        "product": "Coal and coal products", 
        "value": 38.29031342465753
    }, 
    {
        "flow": "Imports", 
        "product": "Crude, NGL and feedstocks", 
        "value": 249.1844946849315
    }, 
    {
        "flow": "Exports", 
        "product": "Coal and coal products", 
        "value": -0.6996635616438357
    }, 
    {
        "flow": "Exports", 
        "product": "Crude, NGL and feedstocks", 
        "value": -0.20222767123287672
    }, 
    {
        "flow": "Total Consumption", 
        "product": "Coal and coal products", 
        "value": 22.17473608219178
    }, 
    {
        "flow": "Total Consumption", 
        "product": "Combustible renewables and waste", 
        "value": 70.85587676712329
    }, 
    {
        "flow": "Imports", 
        "product": "Oil Products", 
        "value": 371.9163679452055
    }, 
    {
        "flow": "Imports", 
        "product": "Electricity", 
        "value": 10.902983397260273
    }, 
    {
        "flow": "Exports", 
        "product": "Oil Products", 
        "value": -39.70851780821918
    }, 
    {
        "flow": "Exports", 
        "product": "Electricity", 
        "value": -9.272630739726026
    }, 
    {
        "flow": "Total Consumption", 
        "product": "Oil Products", 
        "value": 465.7983452328768
    }, 
    {
        "flow": "Total Consumption", 
        "product": "Electricity", 
        "value": 123.76518235616437
    }, 
    {
        "flow": "Production", 
        "product": "Electricity", 
        "value": 195.77215027397258
    }, 
    {
        "flow": "Electricity", 
        "product": "Coal and coal products", 
        "value": -1.0178257260273973
    }, 
    {
        "flow": "Electricity", 
        "product": "Nuclear", 
        "value": -62.640252109589035
    }, 
    {
        "flow": "Electricity", 
        "product": "Hydro", 
        "value": -99.5620444931507
    }, 
    {
        "flow": "Electricity", 
        "product": "Combustible renewables and waste", 
        "value": -0.7639466575342466
    }, 
    {
        "flow": "Electricity", 
        "product": "Oil Products", 
        "value": -31.78808128767123
    }, 
    {
        "flow": "Oil Products", 
        "product": "Crude, NGL and feedstocks", 
        "value": -234.68685920547944
    }, 
    {
        "flow": "Heat and Waste", 
        "product": "All products", 
        "value": 75.63371134246572
    }, 
    {
        "flow": "Industry", 
        "product": "All products", 
        "value": 261.2166997260274
    }, 
    {
        "flow": "Transport", 
        "product": "All products", 
        "value": 108.24980147945205
    }, 
    {
        "flow": "Residential", 
        "product": "All products", 
        "value": 205.35242010958905
    }, 
    {
        "flow": "Commercial", 
        "product": "All products", 
        "value": 22.39041882191781
    }, 
    {
        "flow": "Other", 
        "product": "All products", 
        "value": 104.62584947945206
    }, 
    {
        "flow": "Total Consumption", 
        "product": "All products", 
        "value": 682.5941404383562
    }, 
    {
        "flow": "Production", 
        "product": "All primary", 
        "value": 234.93891079452055
    }, 
    {
        "flow": "Imports", 
        "product": "All primary", 
        "value": 287.47480810958905
    }, 
    {
        "flow": "Exports", 
        "product": "All primary", 
        "value": -0.9018912328767124
    }, 
    {
        "flow": "Total Consumption", 
        "product": "All primary", 
        "value": 93.03061284931508
    }, 
    {
        "flow": "Oil Products", 
        "product": "All primary", 
        "value": -234.68685920547944
    }, 
    {
        "flow": "Electricity", 
        "product": "All primary", 
        "value": -195.77215027397258
    }, 
    {
        "flow": "Production", 
        "product": "Oil Products", 
        "value": 228.42288219178081
    }, 
    {
        "flow": "Hydrocarbon Heat and Waste", 
        "product": "All products", 
        "value": 6.2639770136986215
    }, 
    {
        "flow": "Electricity Heat and Waste", 
        "product": "All products", 
        "value": 69.3697343287671
    }
]
